ldapdb/__init__.py
ldapdb/router.py
ldapdb/tests.py
ldapdb/version.py
ldapdb/backends/__init__.py
ldapdb/backends/ldap/__init__.py
ldapdb/backends/ldap/base.py
ldapdb/backends/ldap/compiler.py
ldapdb/models/__init__.py
ldapdb/models/base.py
ldapdb/models/fields.py
django_ldapdb2-1.5.3.dev0.dist-info/AUTHORS
django_ldapdb2-1.5.3.dev0.dist-info/LICENSE
django_ldapdb2-1.5.3.dev0.dist-info/METADATA
django_ldapdb2-1.5.3.dev0.dist-info/WHEEL
django_ldapdb2-1.5.3.dev0.dist-info/top_level.txt
django_ldapdb2-1.5.3.dev0.dist-info/RECORD
